SpeakerVerSim/__init__.py
SpeakerVerSim/common.py
SpeakerVerSim/server_double.py
SpeakerVerSim/server_single_hash.py
SpeakerVerSim/server_single_multiprofile.py
SpeakerVerSim/server_single_simple.py
SpeakerVerSim/server_single_sync.py
SpeakerVerSim/simulator.py
SpeakerVerSim/test_simulation.py
SpeakerVerSim-0.1.3.dist-info/LICENSE
SpeakerVerSim-0.1.3.dist-info/METADATA
SpeakerVerSim-0.1.3.dist-info/WHEEL
SpeakerVerSim-0.1.3.dist-info/top_level.txt
SpeakerVerSim-0.1.3.dist-info/RECORD
