Metadata-Version: 2.1
Name: SpeakerVerSim
Version: 0.1.3
Summary: Simulation framework for version control strategies of speaker recognition systems.
Home-page: https://github.com/wq2012/SpeakerVerSim
Author: Quan Wang
Author-email: quanw@google.com
Classifier: Programming Language :: Python :: 3
Classifier: License :: OSI Approved :: Apache Software License
Classifier: Operating System :: OS Independent
License-File: LICENSE
Requires-Dist: simpy
Requires-Dist: pyyaml
Requires-Dist: tqdm
Requires-Dist: seaborn
Requires-Dist: munch
